cli/__init__.py
cli/main.py
core/__init__.py
core/config.py
core/context_builder.py
core/filter.py
core/renderer.py
core/writer.py
hooks/__init__.py
hooks/hooks.py
proto/__init__.py
proto/discover.py
proto/fds_loader.py
proto/proto_source.py
proto/protoc_runner.py
utils/__init__.py
utils/name.py
utils/path.py
wizard_codegen-0.1.9.dist-info/METADATA
wizard_codegen-0.1.9.dist-info/WHEEL
wizard_codegen-0.1.9.dist-info/entry_points.txt
wizard_codegen-0.1.9.dist-info/RECORD
