Metadata-Version: 2.4
Name: wizard-codegen
Version: 0.1.9
Summary: A powerful, template-driven code generation tool for Protocol Buffers
Requires-Python: >=3.10
Requires-Dist: click==8.3.1
Requires-Dist: jinja2==3.1.6
Requires-Dist: protobuf==6.33.2
Requires-Dist: pydantic-core==2.41.5
Requires-Dist: pydantic==2.12.5
Requires-Dist: pyyaml==6.0.3
Requires-Dist: rich==14.2.0
Requires-Dist: typer==0.21.0
